gpudb/__init__.py
gpudb/gpudb.py
gpudb/gpudb_dataframe.py
gpudb/gpudb_file_handler.py
gpudb/gpudb_multihead_io.py
gpudb/gpudb_sql_context.py
gpudb/gpudb_sql_iterator.py
gpudb/gpudb_table_monitor.py
gpudb/protocol.cpython-312-i386-linux-gnu.so
gpudb/dbapi/__init__.py
gpudb/dbapi/setup.py
gpudb/dbapi/aio/__init__.py
gpudb/dbapi/aio/connection.py
gpudb/dbapi/aio/cursor.py
gpudb/dbapi/aio/utils.py
gpudb/dbapi/core/__init__.py
gpudb/dbapi/core/connection.py
gpudb/dbapi/core/cursor.py
gpudb/dbapi/core/exceptions.py
gpudb/dbapi/core/types.py
gpudb/dbapi/core/utils.py
gpudb/dbapi/pep249/__init__.py
gpudb/dbapi/pep249/connection.py
gpudb/dbapi/pep249/cursor.py
gpudb/dbapi/pep249/exceptions.py
gpudb/dbapi/pep249/extensions.py
gpudb/dbapi/pep249/transactions.py
gpudb/dbapi/pep249/type_constructors.py
gpudb/dbapi/pep249/types.py
gpudb/dbapi/pep249/aiopep249/__init__.py
gpudb/dbapi/pep249/aiopep249/connection.py
gpudb/dbapi/pep249/aiopep249/cursor.py
gpudb/dbapi/pep249/aiopep249/exceptions.py
gpudb/dbapi/pep249/aiopep249/extensions.py
gpudb/dbapi/pep249/aiopep249/transactions.py
gpudb/dbapi/pep249/aiopep249/type_constructors.py
gpudb/dbapi/pep249/aiopep249/types.py
gpudb/packages/__init__.py
gpudb/packages/enum34.py
gpudb/packages/kinetica_tabulate.py
gpudb/packages/ordereddict.py
gpudb/packages/pymmh3.py
gpudb/packages/avro/__init__.py
gpudb/packages/avro/avro_py2/__init__.py
gpudb/packages/avro/avro_py2/datafile.py
gpudb/packages/avro/avro_py2/io.py
gpudb/packages/avro/avro_py2/ipc.py
gpudb/packages/avro/avro_py2/protocol.py
gpudb/packages/avro/avro_py2/schema.py
gpudb/packages/avro/avro_py2/tool.py
gpudb/packages/avro/avro_py2/txipc.py
gpudb/packages/avro/avro_py3/HandshakeRequest.avsc
gpudb/packages/avro/avro_py3/HandshakeResponse.avsc
gpudb/packages/avro/avro_py3/VERSION.txt
gpudb/packages/avro/avro_py3/__init__.py
gpudb/packages/avro/avro_py3/datafile.py
gpudb/packages/avro/avro_py3/io.py
gpudb-7.2.3.4.dist-info/METADATA
gpudb-7.2.3.4.dist-info/WHEEL
gpudb-7.2.3.4.dist-info/top_level.txt
gpudb-7.2.3.4.dist-info/RECORD
gpudb-7.2.3.4.dist-info/licenses/LICENSE
