Metadata-Version: 2.4
Name: gpudb
Version: 7.2.3.4
Summary: Python client for Kinetica DB
Author-email: "Kinetica DB, Inc." <support@kinetica.com>
Maintainer-email: Kyle Sutton <ksutton@kinetica.com>, Anindya Mukherjee <amukherjee@kinetica.com>
License: MIT License
Project-URL: Homepage, https://www.kinetica.com
Project-URL: Documentation, https://docs.kinetica.com/7.2/api/python/
Keywords: kinetica,gpudb
Classifier: Programming Language :: Python :: 3
Classifier: Topic :: Database
Requires-Python: >=3.8
License-File: LICENSE
Requires-Dist: future
Requires-Dist: pyzmq
Requires-Dist: sqlparse
Requires-Dist: urllib3>=2.0.0
Requires-Dist: requests
Provides-Extra: dataframe
Requires-Dist: pandas; extra == "dataframe"
Requires-Dist: tqdm; extra == "dataframe"
Requires-Dist: typeguard; extra == "dataframe"
Dynamic: license-file
